bernoulli_django
