Metadata-Version: 1.0
Name: bernoulli-django
Version: 0.1.7
Summary: Package to integrate django app with Bernoulli
Home-page: https://github.com/bernoulli-metrics/bernoulli_django
Author: Joe Gasiorek
Author-email: joe.gasiorek@gmail.com
License: MIT
Platform: UNKNOWN
